[
  {
    "name": "三浦 泰嗣",
    "affiliation": "電通国際情報サービス",
    "url": "https://twitter.com/ymym3412",
    "image": "https://pbs.twimg.com/profile_images/882482857179926528/YDwK3X_E_400x400.jpg",
    "date": "2019-01-01"
  },
  {
    "name": "ファイサル ハディプトラ",
    "affiliation": "電通国際情報サービス",
    "url": "https://twitter.com/faisal_putra",
    "image": "https://pbs.twimg.com/profile_images/1409031112/310396067_400x400.jpg",
    "date": "2019-01-01"
  },
  {
    "name": "片岡 裕雄",
    "affiliation": "産業技術総合研究所",
    "url": "http://hirokatsukataoka.net/",
    "image": "http://hirokatsukataoka.net/image/hirokatsu_min.png",
    "date": "2019-01-01"
  }
]
